brutalist_report/__init__.py
brutalist_report/_constants.py
brutalist_report/_helpers.py
brutalist_report/async_fetch.py
brutalist_report/custom_types.py
brutalist_report/fetch.py
brutalist_report_api-0.1.0.dist-info/METADATA
brutalist_report_api-0.1.0.dist-info/WHEEL
brutalist_report_api-0.1.0.dist-info/top_level.txt
brutalist_report_api-0.1.0.dist-info/RECORD
